README.md
_version.txt
ipread.py
setup.py
ipread.egg-info/PKG-INFO
ipread.egg-info/PKG-INFO_conflict-20151026-150157
ipread.egg-info/SOURCES.txt
ipread.egg-info/dependency_links.txt
ipread.egg-info/requires.txt
ipread.egg-info/top_level.txt
scripts/ipread