Metadata-Version: 1.1
Name: ipread
Version: 0.2.1
Summary: Reads Imageplate files and combines multiple readouts to a single HDR if necessary. Can be used as module or with "python -m ipread" to have a CLI tool for fast preview.
Home-page: https://github.com/skuschel/IPread
Author: Stephan Kuschel
Author-email: stephan.kuschel@gmail.com
License: GPL
Platform: UNKNOWN
Classifier: Intended Audience :: Science/Research
Classifier: Topic :: Scientific/Engineering :: Astronomy
Classifier: Topic :: Scientific/Engineering :: Physics
Classifier: Topic :: Scientific/Engineering :: Visualization
